flask_school/__init__.py
Flask_School-0.0.5.dist-info/METADATA
Flask_School-0.0.5.dist-info/WHEEL
Flask_School-0.0.5.dist-info/top_level.txt
Flask_School-0.0.5.dist-info/RECORD
