Metadata-Version: 2.1
Name: Flask-School
Version: 0.0.5
Summary: School SDK extension with flask
Home-page: https://github.com/Farmer-chong/flask-school
Author: farmer.chillax
Author-email: farmer-chong@qq.com
License: MIT
Requires-Dist: Flask
Requires-Dist: school-sdk
